hybridts/__init__.py
hybridts/exc.py
hybridts/tc_state.py
hybridts/type_encoding.py
hybrid_type_system-0.2.dist-info/LICENSE
hybrid_type_system-0.2.dist-info/METADATA
hybrid_type_system-0.2.dist-info/WHEEL
hybrid_type_system-0.2.dist-info/entry_points.txt
hybrid_type_system-0.2.dist-info/top_level.txt
hybrid_type_system-0.2.dist-info/RECORD
