Metadata-Version: 2.1
Name: hybrid-type-system
Version: 0.2
Summary: A composition of advanced type systems
Home-page: https://github.com/RemuLang/hybridts
Author: thautawarm
Author-email: twshere@outlook.com
License: mit
Platform: any
Classifier: Programming Language :: Python :: 3.5
Classifier: Programming Language :: Python :: 3.6
Classifier: Programming Language :: Python :: 3.7
Classifier: Programming Language :: Python :: 3.8
Classifier: Programming Language :: Python :: Implementation :: CPython
Requires-Python: >=3.6.0
